{"_type":"export","__export_format":4,"__export_date":"2020-10-17T18:30:56.564Z","__export_source":"insomnia.desktop.app:v2020.4.1","resources":[{"_id":"req_be1288fdb63e4888a9bf60d04c60a8a7","parentId":"fld_1d37cc241b964fb1b88e3e03be9757f0","modified":1602718413637,"created":1602512754155,"url":"http://localhost:1747/boards/5f8781eb92e9eb3db8f45721","name":"Delete Board","description":"","method":"DELETE","body":{},"parameters":[],"headers":[],"authentication":{},"metaSortKey":-1602450161552.375,"isPrivate":false,"settingStoreCookies":true,"settingSendCookies":true,"settingDisableRenderRequestBody":false,"settingEncodeUrl":true,"settingRebuildPath":true,"settingFollowRedirects":"global","_type":"request"},{"_id":"fld_1d37cc241b964fb1b88e3e03be9757f0","parentId":"fld_887176599d7d452fbb5edc34c76f3fd6","modified":1602540307217,"created":1602540307217,"name":"boards","description":"","environment":{},"environmentPropertyOrder":null,"metaSortKey":-1602540307217,"_type":"request_group"},{"_id":"fld_887176599d7d452fbb5edc34c76f3fd6","parentId":"wrk_23c1ed9f8ade47b3aa05d0869a67b66a","modified":1602512672798,"created":1602512672798,"name":"Kanban","description":"","environment":{},"environmentPropertyOrder":null,"metaSortKey":-1602512672798,"_type":"request_group"},{"_id":"wrk_23c1ed9f8ade47b3aa05d0869a67b66a","parentId":null,"modified":1599591635250,"created":1597328312675,"name":"Insomnia","description":"voting app ","scope":null,"_type":"workspace"},{"_id":"req_314470804fd6404d81981d343ee33b0c","parentId":"fld_1d37cc241b964fb1b88e3e03be9757f0","modified":1602718402018,"created":1602512743620,"url":"http://localhost:1747/boards/5f8781eb92e9eb3db8f45721","name":"Update Board","description":"","method":"PATCH","body":{"mimeType":"application/json","text":"{\n\t\"title\": \"Board To Update 333333\",\n\t\"description\": \"Board description\"\n}"},"parameters":[],"headers":[{"name":"Content-Type","value":"application/json","id":"pair_8099e21d62224978bd3992986e77e0a8"}],"authentication":{},"metaSortKey":-1602450161502.375,"isPrivate":false,"settingStoreCookies":true,"settingSendCookies":true,"settingDisableRenderRequestBody":false,"settingEncodeUrl":true,"settingRebuildPath":true,"settingFollowRedirects":"global","_type":"request"},{"_id":"req_ceeecacadc9046bb949f329ed2125316","parentId":"fld_1d37cc241b964fb1b88e3e03be9757f0","modified":1602716452076,"created":1602512729187,"url":"http://localhost:1747/boards","name":"Insert Board","description":"","method":"POST","body":{"mimeType":"application/json","text":"{\n\t\"title\":\"new Board\",\n\t\"description\": \"board test\"\n}"},"parameters":[],"headers":[{"name":"Content-Type","value":"application/json","id":"pair_02e8df0b53a74e3e953b9ee011383def"},{"name":"oioioio","value":"123","description":"","id":"pair_df7714afbc0e4659b9f43523909b9851"}],"authentication":{},"metaSortKey":-1602450161452.375,"isPrivate":false,"settingStoreCookies":true,"settingSendCookies":true,"settingDisableRenderRequestBody":false,"settingEncodeUrl":true,"settingRebuildPath":true,"settingFollowRedirects":"global","_type":"request"},{"_id":"req_1ee13f9b9b1f41f28d939e57c5a510a9","parentId":"fld_1d37cc241b964fb1b88e3e03be9757f0","modified":1602940754721,"created":1602512708764,"url":"http://localhost:1747/boards/5f8aef2c97ed6b260cc0e920","name":"Get Board By Id","description":"","method":"GET","body":{},"parameters":[],"headers":[],"authentication":{},"metaSortKey":-1602450161427.375,"isPrivate":false,"settingStoreCookies":true,"settingSendCookies":true,"settingDisableRenderRequestBody":false,"settingEncodeUrl":true,"settingRebuildPath":true,"settingFollowRedirects":"global","_type":"request"},{"_id":"req_59b6ed202ba745a4ae0dec845fbfc2da","parentId":"fld_1d37cc241b964fb1b88e3e03be9757f0","modified":1602540313453,"created":1602512683223,"url":"http://localhost:1747/boards","name":"Get Boards","description":"","method":"GET","body":{},"parameters":[],"headers":[],"authentication":{},"metaSortKey":-1602450161402.375,"isPrivate":false,"settingStoreCookies":true,"settingSendCookies":true,"settingDisableRenderRequestBody":false,"settingEncodeUrl":true,"settingRebuildPath":true,"settingFollowRedirects":"global","_type":"request"},{"_id":"req_55546c8c3e594512a233f01b7da3c70f","parentId":"fld_67d7524d419b4c10b926734dea685e37","modified":1602804384309,"created":1602540343045,"url":"http://localhost:1747/tasks/5f88d0b182f7ca05409919e3","name":"Delete Task","description":"","method":"DELETE","body":{},"parameters":[],"headers":[],"authentication":{},"metaSortKey":-1602450161552.375,"isPrivate":false,"settingStoreCookies":true,"settingSendCookies":true,"settingDisableRenderRequestBody":false,"settingEncodeUrl":true,"settingRebuildPath":true,"settingFollowRedirects":"global","_type":"request"},{"_id":"fld_67d7524d419b4c10b926734dea685e37","parentId":"fld_887176599d7d452fbb5edc34c76f3fd6","modified":1602540342998,"created":1602540342998,"name":"tasks","description":"","environment":{},"environmentPropertyOrder":null,"metaSortKey":-1602526490007.5,"_type":"request_group"},{"_id":"req_0064511a76e44163aa72c46b6ace5cd1","parentId":"fld_67d7524d419b4c10b926734dea685e37","modified":1602804363782,"created":1602540343041,"url":"http://localhost:1747/tasks/5f8791076edb2819587703cf","name":"Update Task","description":"","method":"PATCH","body":{"mimeType":"application/json","text":"{\n\t\"title\":\"Updated task\",\n\t\"description\": \"desc Task\",\n\t\"status\": \"DOING\"\n}"},"parameters":[],"headers":[{"name":"Content-Type","value":"application/json","id":"pair_8099e21d62224978bd3992986e77e0a8"}],"authentication":{},"metaSortKey":-1602450161502.375,"isPrivate":false,"settingStoreCookies":true,"settingSendCookies":true,"settingDisableRenderRequestBody":false,"settingEncodeUrl":true,"settingRebuildPath":true,"settingFollowRedirects":"global","_type":"request"},{"_id":"req_2ecd533f964a436993d5e83e9829d281","parentId":"fld_67d7524d419b4c10b926734dea685e37","modified":1602720005891,"created":1602540343037,"url":"http://localhost:1747/tasks/5f8631e13beac81c30800180","name":"Insert Task","description":"","method":"POST","body":{"mimeType":"application/json","text":"{\n\t\"title\":\"oi\",\n\t\"description\": \"true\",\n\t\"status\": \"TO DO\"\n}"},"parameters":[],"headers":[{"name":"Content-Type","value":"application/json","id":"pair_02e8df0b53a74e3e953b9ee011383def"},{"name":"oioioio","value":"123","description":"","id":"pair_df7714afbc0e4659b9f43523909b9851"}],"authentication":{},"metaSortKey":-1602450161452.375,"isPrivate":false,"settingStoreCookies":true,"settingSendCookies":true,"settingDisableRenderRequestBody":false,"settingEncodeUrl":true,"settingRebuildPath":true,"settingFollowRedirects":"global","_type":"request"},{"_id":"req_c17a3c64f49e4988929ffc97ca26fa66","parentId":"fld_67d7524d419b4c10b926734dea685e37","modified":1602802474115,"created":1602540343032,"url":"http://localhost:1747/tasks/5f8631e13beac81c30800180/5f8791076edb2819587703cf","name":"Get Task By Id","description":"","method":"GET","body":{},"parameters":[],"headers":[],"authentication":{},"metaSortKey":-1602450161427.375,"isPrivate":false,"settingStoreCookies":true,"settingSendCookies":true,"settingDisableRenderRequestBody":false,"settingEncodeUrl":true,"settingRebuildPath":true,"settingFollowRedirects":"global","_type":"request"},{"_id":"req_78cac33e4ad642fa96faa5851617059a","parentId":"fld_67d7524d419b4c10b926734dea685e37","modified":1602801880802,"created":1602540343020,"url":"http://localhost:1747/tasks/5f8631e13beac81c30800180","name":"Get Task","description":"","method":"GET","body":{},"parameters":[],"headers":[],"authentication":{},"metaSortKey":-1602450161402.375,"isPrivate":false,"settingStoreCookies":true,"settingSendCookies":true,"settingDisableRenderRequestBody":false,"settingEncodeUrl":true,"settingRebuildPath":true,"settingFollowRedirects":"global","_type":"request"},{"_id":"env_6e199d222b9ea5a61a5450989f7377608850936e","parentId":"wrk_23c1ed9f8ade47b3aa05d0869a67b66a","modified":1597328312781,"created":1597328312781,"name":"Base Environment","data":{},"dataPropertyOrder":null,"color":null,"isPrivate":false,"metaSortKey":1597328312781,"_type":"environment"},{"_id":"jar_6e199d222b9ea5a61a5450989f7377608850936e","parentId":"wrk_23c1ed9f8ade47b3aa05d0869a67b66a","modified":1597328312786,"created":1597328312786,"name":"Default Jar","cookies":[],"_type":"cookie_jar"},{"_id":"spc_6b0ccebdce484b63b75608d90dbad740","parentId":"wrk_23c1ed9f8ade47b3aa05d0869a67b66a","modified":1597328312678,"created":1597328312678,"fileName":"Insomnia","contents":"","contentType":"yaml","_type":"api_spec"}]}